incipyt/__init__.py
incipyt/__main__.py
incipyt/commands.py
incipyt/signals.py
incipyt/_internal/__init__.py
incipyt/_internal/dumpers.py
incipyt/_internal/sanitizers.py
incipyt/_internal/templates.py
incipyt/_internal/utils.py
incipyt/project/__init__.py
incipyt/project/environment.py
incipyt/project/meta_variables.py
incipyt/project/structure.py
incipyt/templates/README.md
incipyt/templates/python.gitignore
incipyt/templates/licenses/Apache-2.0.txt
incipyt/templates/licenses/BSD-2-Clause.txt
incipyt/templates/licenses/BSD-3-Clause.txt
incipyt/templates/licenses/CDDL-1.0.txt
incipyt/templates/licenses/Copyright.txt
incipyt/templates/licenses/EPL-2.0.txt
incipyt/templates/licenses/GPL-2.0.txt
incipyt/templates/licenses/GPL-3.0.txt
incipyt/templates/licenses/LGPL-2.0.txt
incipyt/templates/licenses/LGPL-2.1.txt
incipyt/templates/licenses/LGPL-3.0.txt
incipyt/templates/licenses/MIT.txt
incipyt/templates/licenses/MPL-2.0.txt
incipyt/templates/{PROJECT_NAME}/__init__.py
incipyt/tools/__init__.py
incipyt/tools/base.py
incipyt/tools/git.py
incipyt/tools/license.py
incipyt/tools/poetry.py
incipyt/tools/venv.py
incipyt/tools/pep517/__init__.py
incipyt/tools/pep517/base.py
incipyt/tools/pep517/flit.py
incipyt/tools/pep517/hatch.py
incipyt/tools/pep517/pdm.py
incipyt/tools/pep517/setuptools.py
incipyt-0.4.0.dist-info/entry_points.txt
incipyt-0.4.0.dist-info/LICENSE
incipyt-0.4.0.dist-info/WHEEL
incipyt-0.4.0.dist-info/METADATA
incipyt-0.4.0.dist-info/RECORD
