Metadata-Version: 2.1
Name: incipyt
Version: 0.4.0
Summary: incipyt is a command-line tool that bootstraps a python project.
Author-email: Not at Name <julien@drlazor.be>
Maintainer-email: Not at Name <julien@drlazor.be>
Requires-Python: >=3.8, <4.0
Classifier: Development Status :: 3 - Alpha
Classifier: Environment :: Console
Classifier: Intended Audience :: Developers
Classifier: License :: OSI Approved :: MIT License
Classifier: Operating System :: OS Independent
Classifier: Programming Language :: Python :: 3 :: Only
Classifier: Topic :: Software Development
Requires-Dist: click
Requires-Dist: signalslot
Requires-Dist: tomli_w
Requires-Dist: tomli; python_version<'3.11'
Requires-Dist: flit==3.9.0 ; extra == "dev"
Requires-Dist: pre-commit==3.3.2 ; extra == "dev"
Requires-Dist: m2r2==0.3.2 ; extra == "doc"
Requires-Dist: sphinxcontrib-apidoc==0.3.0 ; extra == "doc"
Requires-Dist: sphinx_rtd_theme==1.2.1 ; extra == "doc"
Requires-Dist: pytest-cov==4.1.0 ; extra == "test"
Requires-Dist: pytest-subprocess==1.5.0 ; extra == "test"
Project-URL: documentation, https://github.com/NotANameServer/incipyt/wiki
Project-URL: homepage, https://pypi.org/incipyt
Project-URL: repository, https://github.com/NotANameServer/incipyt
Provides-Extra: dev
Provides-Extra: doc
Provides-Extra: test
